{"16M": {"sa1": {"23": ["data\\volunteers\\16M\\Clips\\straightcam\\sa1\\24.png", "sh"], "24": ["data\\volunteers\\16M\\Clips\\straightcam\\sa1\\25.png", "sh"], "25": ["data\\volunteers\\16M\\Clips\\straightcam\\sa1\\26.png", "sh"], "26": ["data\\volunteers\\16M\\Clips\\straightcam\\sa1\\27.png", "sh"], "27": ["data\\volunteers\\16M\\Clips\\straightcam\\sa1\\28.png", "sh"], "28": ["data\\volunteers\\16M\\Clips\\straightcam\\sa1\\29.png", "iy"], "29": ["data\\volunteers\\16M\\Clips\\straightcam\\sa1\\30.png", "iy"], "30": ["data\\volunteers\\16M\\Clips\\straightcam\\sa1\\31.png", "hh"], "31": ["data\\volunteers\\16M\\Clips\\straightcam\\sa1\\32.png", "hh"], "32": ["data\\volunteers\\16M\\Clips\\straightcam\\sa1\\33.png", "ae"], "33": ["data\\volunteers\\16M\\Clips\\straightcam\\sa1\\34.png", "ae"], "34": ["data\\volunteers\\16M\\Clips\\straightcam\\sa1\\35.png", "ae"], "35": ["data\\volunteers\\16M\\Clips\\straightcam\\sa1\\36.png", "ae"], "36": ["data\\volunteers\\16M\\Clips\\straightcam\\sa1\\37.png", "d"], "37": ["data\\volunteers\\16M\\Clips\\straightcam\\sa1\\38.png", "d"], "38": ["data\\volunteers\\16M\\Clips\\straightcam\\sa1\\39.png", "y"], "39": ["data\\volunteers\\16M\\Clips\\straightcam\\sa1\\40.png", "uh"], "40": ["data\\volunteers\\16M\\Clips\\straightcam\\sa1\\41.png", "r"], "41": ["data\\volunteers\\16M\\Clips\\straightcam\\sa1\\42.png", "d"], "42": ["data\\volunteers\\16M\\Clips\\straightcam\\sa1\\43.png", "d"], "43": ["data\\volunteers\\16M\\Clips\\straightcam\\sa1\\44.png", "d"], "44": ["data\\volunteers\\16M\\Clips\\straightcam\\sa1\\45.png", "aa"], "45": ["data\\volunteers\\16M\\Clips\\straightcam\\sa1\\46.png", "aa"], "46": ["data\\volunteers\\16M\\Clips\\straightcam\\sa1\\47.png", "r"], "47": ["data\\volunteers\\16M\\Clips\\straightcam\\sa1\\48.png", "r"], "48": ["data\\volunteers\\16M\\Clips\\straightcam\\sa1\\49.png", "r"], "49": ["data\\volunteers\\16M\\Clips\\straightcam\\sa1\\50.png", "r"], "50": ["data\\volunteers\\16M\\Clips\\straightcam\\sa1\\51.png", "k"], "51": ["data\\volunteers\\16M\\Clips\\straightcam\\sa1\\52.png", "s"], "52": ["data\\volunteers\\16M\\Clips\\straightcam\\sa1\\53.png", "s"], "53": ["data\\volunteers\\16M\\Clips\\straightcam\\sa1\\54.png", "s"], "54": ["data\\volunteers\\16M\\Clips\\straightcam\\sa1\\55.png", "s"], "55": ["data\\volunteers\\16M\\Clips\\straightcam\\sa1\\56.png", "uw"], "56": ["data\\volunteers\\16M\\Clips\\straightcam\\sa1\\57.png", "uw"], "57": ["data\\volunteers\\16M\\Clips\\straightcam\\sa1\\58.png", "uw"], "58": ["data\\volunteers\\16M\\Clips\\straightcam\\sa1\\59.png", "uw"], "59": ["data\\volunteers\\16M\\Clips\\straightcam\\sa1\\60.png", "t"], "60": ["data\\volunteers\\16M\\Clips\\straightcam\\sa1\\61.png", "t"], "61": ["data\\volunteers\\16M\\Clips\\straightcam\\sa1\\62.png", "t"], "62": ["data\\volunteers\\16M\\Clips\\straightcam\\sa1\\63.png", "t"], "63": ["data\\volunteers\\16M\\Clips\\straightcam\\sa1\\64.png", "t"], "64": ["data\\volunteers\\16M\\Clips\\straightcam\\sa1\\65.png", "t"], "65": ["data\\volunteers\\16M\\Clips\\straightcam\\sa1\\66.png", "ah"], "66": ["data\\volunteers\\16M\\Clips\\straightcam\\sa1\\67.png", "n"], "67": ["data\\volunteers\\16M\\Clips\\straightcam\\sa1\\68.png", "n"], "68": ["data\\volunteers\\16M\\Clips\\straightcam\\sa1\\69.png", "n"], "69": ["data\\volunteers\\16M\\Clips\\straightcam\\sa1\\70.png", "g"], "70": ["data\\volunteers\\16M\\Clips\\straightcam\\sa1\\71.png", "g"], "71": ["data\\volunteers\\16M\\Clips\\straightcam\\sa1\\72.png", "r"], "72": ["data\\volunteers\\16M\\Clips\\straightcam\\sa1\\73.png", "r"], "73": ["data\\volunteers\\16M\\Clips\\straightcam\\sa1\\74.png", "iy"], "74": ["data\\volunteers\\16M\\Clips\\straightcam\\sa1\\75.png", "s"], "75": ["data\\volunteers\\16M\\Clips\\straightcam\\sa1\\76.png", "s"], "76": ["data\\volunteers\\16M\\Clips\\straightcam\\sa1\\77.png", "s"], "77": ["data\\volunteers\\16M\\Clips\\straightcam\\sa1\\78.png", "s"], "78": ["data\\volunteers\\16M\\Clips\\straightcam\\sa1\\79.png", "iy"], "79": ["data\\volunteers\\16M\\Clips\\straightcam\\sa1\\80.png", "iy"], "80": ["data\\volunteers\\16M\\Clips\\straightcam\\sa1\\81.png", "w"], "81": ["data\\volunteers\\16M\\Clips\\straightcam\\sa1\\82.png", "w"], "82": ["data\\volunteers\\16M\\Clips\\straightcam\\sa1\\83.png", "w"], "83": ["data\\volunteers\\16M\\Clips\\straightcam\\sa1\\84.png", "w"], "84": ["data\\volunteers\\16M\\Clips\\straightcam\\sa1\\85.png", "aa"], "85": ["data\\volunteers\\16M\\Clips\\straightcam\\sa1\\86.png", "aa"], "86": ["data\\volunteers\\16M\\Clips\\straightcam\\sa1\\87.png", "sh"], "87": ["data\\volunteers\\16M\\Clips\\straightcam\\sa1\\88.png", "sh"], "88": ["data\\volunteers\\16M\\Clips\\straightcam\\sa1\\89.png", "sh"], "89": ["data\\volunteers\\16M\\Clips\\straightcam\\sa1\\90.png", "w"], "90": ["data\\volunteers\\16M\\Clips\\straightcam\\sa1\\91.png", "w"], "91": ["data\\volunteers\\16M\\Clips\\straightcam\\sa1\\92.png", "w"], "92": ["data\\volunteers\\16M\\Clips\\straightcam\\sa1\\93.png", "aa"], "93": ["data\\volunteers\\16M\\Clips\\straightcam\\sa1\\94.png", "aa"], "94": ["data\\volunteers\\16M\\Clips\\straightcam\\sa1\\95.png", "aa"], "95": ["data\\volunteers\\16M\\Clips\\straightcam\\sa1\\96.png", "t"], "96": ["data\\volunteers\\16M\\Clips\\straightcam\\sa1\\97.png", "er"], "97": ["data\\volunteers\\16M\\Clips\\straightcam\\sa1\\98.png", "er"], "98": ["data\\volunteers\\16M\\Clips\\straightcam\\sa1\\99.png", "er"], "99": ["data\\volunteers\\16M\\Clips\\straightcam\\sa1\\100.png", "er"], "100": ["data\\volunteers\\16M\\Clips\\straightcam\\sa1\\101.png", "er"], "101": ["data\\volunteers\\16M\\Clips\\straightcam\\sa1\\102.png", "aa"], "102": ["data\\volunteers\\16M\\Clips\\straightcam\\sa1\\103.png", "aa"], "103": ["data\\volunteers\\16M\\Clips\\straightcam\\sa1\\104.png", "aa"], "104": ["data\\volunteers\\16M\\Clips\\straightcam\\sa1\\105.png", "aa"], "105": ["data\\volunteers\\16M\\Clips\\straightcam\\sa1\\106.png", "aa"], "106": ["data\\volunteers\\16M\\Clips\\straightcam\\sa1\\107.png", "l"], "107": ["data\\volunteers\\16M\\Clips\\straightcam\\sa1\\108.png", "y"], "108": ["data\\volunteers\\16M\\Clips\\straightcam\\sa1\\109.png", "ih"], "109": ["data\\volunteers\\16M\\Clips\\straightcam\\sa1\\110.png", "ih"], "110": ["data\\volunteers\\16M\\Clips\\straightcam\\sa1\\111.png", "ih"], "111": ["data\\volunteers\\16M\\Clips\\straightcam\\sa1\\112.png", "ih"], "112": ["data\\volunteers\\16M\\Clips\\straightcam\\sa1\\113.png", "ih"], "113": ["data\\volunteers\\16M\\Clips\\straightcam\\sa1\\114.png", "r"]}, "sa2": {"30": ["data\\volunteers\\16M\\Clips\\straightcam\\sa2\\31.png", "d"], "31": ["data\\volunteers\\16M\\Clips\\straightcam\\sa2\\32.png", "d"], "32": ["data\\volunteers\\16M\\Clips\\straightcam\\sa2\\33.png", "ow"], "33": ["data\\volunteers\\16M\\Clips\\straightcam\\sa2\\34.png", "ow"], "34": ["data\\volunteers\\16M\\Clips\\straightcam\\sa2\\35.png", "ow"], "35": ["data\\volunteers\\16M\\Clips\\straightcam\\sa2\\36.png", "n"], "36": ["data\\volunteers\\16M\\Clips\\straightcam\\sa2\\37.png", "ae"], "37": ["data\\volunteers\\16M\\Clips\\straightcam\\sa2\\38.png", "ae"], "38": ["data\\volunteers\\16M\\Clips\\straightcam\\sa2\\39.png", "ae"], "39": ["data\\volunteers\\16M\\Clips\\straightcam\\sa2\\40.png", "ae"], "40": ["data\\volunteers\\16M\\Clips\\straightcam\\sa2\\41.png", "s"], "41": ["data\\volunteers\\16M\\Clips\\straightcam\\sa2\\42.png", "s"], "42": ["data\\volunteers\\16M\\Clips\\straightcam\\sa2\\43.png", "s"], "43": ["data\\volunteers\\16M\\Clips\\straightcam\\sa2\\44.png", "k"], "44": ["data\\volunteers\\16M\\Clips\\straightcam\\sa2\\45.png", "m"], "45": ["data\\volunteers\\16M\\Clips\\straightcam\\sa2\\46.png", "iy"], "46": ["data\\volunteers\\16M\\Clips\\straightcam\\sa2\\47.png", "iy"], "47": ["data\\volunteers\\16M\\Clips\\straightcam\\sa2\\48.png", "t"], "48": ["data\\volunteers\\16M\\Clips\\straightcam\\sa2\\49.png", "t"], "49": ["data\\volunteers\\16M\\Clips\\straightcam\\sa2\\50.png", "ih"], "50": ["data\\volunteers\\16M\\Clips\\straightcam\\sa2\\51.png", "ih"], "51": ["data\\volunteers\\16M\\Clips\\straightcam\\sa2\\52.png", "k"], "52": ["data\\volunteers\\16M\\Clips\\straightcam\\sa2\\53.png", "k"], "53": ["data\\volunteers\\16M\\Clips\\straightcam\\sa2\\54.png", "k"], "54": ["data\\volunteers\\16M\\Clips\\straightcam\\sa2\\55.png", "ae"], "55": ["data\\volunteers\\16M\\Clips\\straightcam\\sa2\\56.png", "r"], "56": ["data\\volunteers\\16M\\Clips\\straightcam\\sa2\\57.png", "r"], "57": ["data\\volunteers\\16M\\Clips\\straightcam\\sa2\\58.png", "iy"], "58": ["data\\volunteers\\16M\\Clips\\straightcam\\sa2\\59.png", "iy"], "59": ["data\\volunteers\\16M\\Clips\\straightcam\\sa2\\60.png", "iy"], "60": ["data\\volunteers\\16M\\Clips\\straightcam\\sa2\\61.png", "ae"], "61": ["data\\volunteers\\16M\\Clips\\straightcam\\sa2\\62.png", "ae"], "62": ["data\\volunteers\\16M\\Clips\\straightcam\\sa2\\63.png", "n"], "63": ["data\\volunteers\\16M\\Clips\\straightcam\\sa2\\64.png", "n"], "64": ["data\\volunteers\\16M\\Clips\\straightcam\\sa2\\65.png", "n"], "65": ["data\\volunteers\\16M\\Clips\\straightcam\\sa2\\66.png", "oy"], "66": ["data\\volunteers\\16M\\Clips\\straightcam\\sa2\\67.png", "oy"], "67": ["data\\volunteers\\16M\\Clips\\straightcam\\sa2\\68.png", "oy"], "68": ["data\\volunteers\\16M\\Clips\\straightcam\\sa2\\69.png", "oy"], "69": ["data\\volunteers\\16M\\Clips\\straightcam\\sa2\\70.png", "l"], "70": ["data\\volunteers\\16M\\Clips\\straightcam\\sa2\\71.png", "iy"], "71": ["data\\volunteers\\16M\\Clips\\straightcam\\sa2\\72.png", "iy"], "72": ["data\\volunteers\\16M\\Clips\\straightcam\\sa2\\73.png", "iy"], "73": ["data\\volunteers\\16M\\Clips\\straightcam\\sa2\\74.png", "iy"], "74": ["data\\volunteers\\16M\\Clips\\straightcam\\sa2\\75.png", "r"], "75": ["data\\volunteers\\16M\\Clips\\straightcam\\sa2\\76.png", "r"], "76": ["data\\volunteers\\16M\\Clips\\straightcam\\sa2\\77.png", "r"], "77": ["data\\volunteers\\16M\\Clips\\straightcam\\sa2\\78.png", "r"], "78": ["data\\volunteers\\16M\\Clips\\straightcam\\sa2\\79.png", "ae"], "79": ["data\\volunteers\\16M\\Clips\\straightcam\\sa2\\80.png", "ae"], "80": ["data\\volunteers\\16M\\Clips\\straightcam\\sa2\\81.png", "ae"], "81": ["data\\volunteers\\16M\\Clips\\straightcam\\sa2\\82.png", "ae"], "82": ["data\\volunteers\\16M\\Clips\\straightcam\\sa2\\83.png", "ae"], "83": ["data\\volunteers\\16M\\Clips\\straightcam\\sa2\\84.png", "g"], "84": ["data\\volunteers\\16M\\Clips\\straightcam\\sa2\\85.png", "g"], "85": ["data\\volunteers\\16M\\Clips\\straightcam\\sa2\\86.png", "l"], "86": ["data\\volunteers\\16M\\Clips\\straightcam\\sa2\\87.png", "ay"], "87": ["data\\volunteers\\16M\\Clips\\straightcam\\sa2\\88.png", "ay"], "88": ["data\\volunteers\\16M\\Clips\\straightcam\\sa2\\89.png", "ay"], "89": ["data\\volunteers\\16M\\Clips\\straightcam\\sa2\\90.png", "k"], "91": ["data\\volunteers\\16M\\Clips\\straightcam\\sa2\\92.png", "dh"], "92": ["data\\volunteers\\16M\\Clips\\straightcam\\sa2\\93.png", "ae"], "93": ["data\\volunteers\\16M\\Clips\\straightcam\\sa2\\94.png", "ae"], "94": ["data\\volunteers\\16M\\Clips\\straightcam\\sa2\\95.png", "ae"], "95": ["data\\volunteers\\16M\\Clips\\straightcam\\sa2\\96.png", "ae"], "96": ["data\\volunteers\\16M\\Clips\\straightcam\\sa2\\97.png", "t"], "97": ["data\\volunteers\\16M\\Clips\\straightcam\\sa2\\98.png", "t"], "98": ["data\\volunteers\\16M\\Clips\\straightcam\\sa2\\99.png", "t"]}, "si455": {"30": ["data\\volunteers\\16M\\Clips\\straightcam\\si455\\31.png", "hh"], "31": ["data\\volunteers\\16M\\Clips\\straightcam\\si455\\32.png", "hh"], "32": ["data\\volunteers\\16M\\Clips\\straightcam\\si455\\33.png", "hh"], "33": ["data\\volunteers\\16M\\Clips\\straightcam\\si455\\34.png", "w"], "34": ["data\\volunteers\\16M\\Clips\\straightcam\\si455\\35.png", "w"], "35": ["data\\volunteers\\16M\\Clips\\straightcam\\si455\\36.png", "ah"], "36": ["data\\volunteers\\16M\\Clips\\straightcam\\si455\\37.png", "n"], "37": ["data\\volunteers\\16M\\Clips\\straightcam\\si455\\38.png", "n"], "38": ["data\\volunteers\\16M\\Clips\\straightcam\\si455\\39.png", "n"], "39": ["data\\volunteers\\16M\\Clips\\straightcam\\si455\\40.png", "n"], "40": ["data\\volunteers\\16M\\Clips\\straightcam\\si455\\41.png", "v"], "41": ["data\\volunteers\\16M\\Clips\\straightcam\\si455\\42.png", "v"], "42": ["data\\volunteers\\16M\\Clips\\straightcam\\si455\\43.png", "ae"], "43": ["data\\volunteers\\16M\\Clips\\straightcam\\si455\\44.png", "ae"], "44": ["data\\volunteers\\16M\\Clips\\straightcam\\si455\\45.png", "ae"], "45": ["data\\volunteers\\16M\\Clips\\straightcam\\si455\\46.png", "l"], "46": ["data\\volunteers\\16M\\Clips\\straightcam\\si455\\47.png", "ah"], "47": ["data\\volunteers\\16M\\Clips\\straightcam\\si455\\48.png", "ah"], "48": ["data\\volunteers\\16M\\Clips\\straightcam\\si455\\49.png", "d"], "49": ["data\\volunteers\\16M\\Clips\\straightcam\\si455\\50.png", "d"], "50": ["data\\volunteers\\16M\\Clips\\straightcam\\si455\\51.png", "ey"], "51": ["data\\volunteers\\16M\\Clips\\straightcam\\si455\\52.png", "ey"], "52": ["data\\volunteers\\16M\\Clips\\straightcam\\si455\\53.png", "t"], "53": ["data\\volunteers\\16M\\Clips\\straightcam\\si455\\54.png", "t"], "54": ["data\\volunteers\\16M\\Clips\\straightcam\\si455\\55.png", "ah"], "55": ["data\\volunteers\\16M\\Clips\\straightcam\\si455\\56.png", "ah"], "56": ["data\\volunteers\\16M\\Clips\\straightcam\\si455\\57.png", "d"], "57": ["data\\volunteers\\16M\\Clips\\straightcam\\si455\\58.png", "d"], "58": ["data\\volunteers\\16M\\Clips\\straightcam\\si455\\59.png", "d"], "59": ["data\\volunteers\\16M\\Clips\\straightcam\\si455\\60.png", "d"], "60": ["data\\volunteers\\16M\\Clips\\straightcam\\si455\\61.png", "d"], "61": ["data\\volunteers\\16M\\Clips\\straightcam\\si455\\62.png", "d"], "62": ["data\\volunteers\\16M\\Clips\\straightcam\\si455\\63.png", "ae"], "63": ["data\\volunteers\\16M\\Clips\\straightcam\\si455\\64.png", "ae"], "64": ["data\\volunteers\\16M\\Clips\\straightcam\\si455\\65.png", "k"], "65": ["data\\volunteers\\16M\\Clips\\straightcam\\si455\\66.png", "k"], "66": ["data\\volunteers\\16M\\Clips\\straightcam\\si455\\67.png", "k"], "67": ["data\\volunteers\\16M\\Clips\\straightcam\\si455\\68.png", "k"], "68": ["data\\volunteers\\16M\\Clips\\straightcam\\si455\\69.png", "s"], "69": ["data\\volunteers\\16M\\Clips\\straightcam\\si455\\70.png", "s"], "70": ["data\\volunteers\\16M\\Clips\\straightcam\\si455\\71.png", "ah"], "71": ["data\\volunteers\\16M\\Clips\\straightcam\\si455\\72.png", "ah"], "72": ["data\\volunteers\\16M\\Clips\\straightcam\\si455\\73.png", "s"], "73": ["data\\volunteers\\16M\\Clips\\straightcam\\si455\\74.png", "s"], "74": ["data\\volunteers\\16M\\Clips\\straightcam\\si455\\75.png", "s"], "75": ["data\\volunteers\\16M\\Clips\\straightcam\\si455\\76.png", "k"], "76": ["data\\volunteers\\16M\\Clips\\straightcam\\si455\\77.png", "k"], "77": ["data\\volunteers\\16M\\Clips\\straightcam\\si455\\78.png", "k"], "78": ["data\\volunteers\\16M\\Clips\\straightcam\\si455\\79.png", "uw"], "79": ["data\\volunteers\\16M\\Clips\\straightcam\\si455\\80.png", "uw"], "80": ["data\\volunteers\\16M\\Clips\\straightcam\\si455\\81.png", "uw"], "81": ["data\\volunteers\\16M\\Clips\\straightcam\\si455\\82.png", "uw"], "82": ["data\\volunteers\\16M\\Clips\\straightcam\\si455\\83.png", "l"], "83": ["data\\volunteers\\16M\\Clips\\straightcam\\si455\\84.png", "d"], "84": ["data\\volunteers\\16M\\Clips\\straightcam\\si455\\85.png", "d"], "85": ["data\\volunteers\\16M\\Clips\\straightcam\\si455\\86.png", "ih"], "86": ["data\\volunteers\\16M\\Clips\\straightcam\\si455\\87.png", "ih"], "87": ["data\\volunteers\\16M\\Clips\\straightcam\\si455\\88.png", "s"], "88": ["data\\volunteers\\16M\\Clips\\straightcam\\si455\\89.png", "s"], "89": ["data\\volunteers\\16M\\Clips\\straightcam\\si455\\90.png", "s"], "90": ["data\\volunteers\\16M\\Clips\\straightcam\\si455\\91.png", "s"], "91": ["data\\volunteers\\16M\\Clips\\straightcam\\si455\\92.png", "s"], "92": ["data\\volunteers\\16M\\Clips\\straightcam\\si455\\93.png", "s"], "93": ["data\\volunteers\\16M\\Clips\\straightcam\\si455\\94.png", "t"], "94": ["data\\volunteers\\16M\\Clips\\straightcam\\si455\\95.png", "r"], "95": ["data\\volunteers\\16M\\Clips\\straightcam\\si455\\96.png", "ih"], "96": ["data\\volunteers\\16M\\Clips\\straightcam\\si455\\97.png", "k"], "97": ["data\\volunteers\\16M\\Clips\\straightcam\\si455\\98.png", "t"], "98": ["data\\volunteers\\16M\\Clips\\straightcam\\si455\\99.png", "t"], "99": ["data\\volunteers\\16M\\Clips\\straightcam\\si455\\100.png", "s"], "100": ["data\\volunteers\\16M\\Clips\\straightcam\\si455\\101.png", "s"], "101": ["data\\volunteers\\16M\\Clips\\straightcam\\si455\\102.png", "s"], "102": ["data\\volunteers\\16M\\Clips\\straightcam\\si455\\103.png", "s"]}, "si456": {"30": ["data\\volunteers\\16M\\Clips\\straightcam\\si456\\31.png", "t"], "31": ["data\\volunteers\\16M\\Clips\\straightcam\\si456\\32.png", "t"], "32": ["data\\volunteers\\16M\\Clips\\straightcam\\si456\\33.png", "t"], "33": ["data\\volunteers\\16M\\Clips\\straightcam\\si456\\34.png", "uw"], "34": ["data\\volunteers\\16M\\Clips\\straightcam\\si456\\35.png", "uw"], "35": ["data\\volunteers\\16M\\Clips\\straightcam\\si456\\36.png", "uw"], "36": ["data\\volunteers\\16M\\Clips\\straightcam\\si456\\37.png", "uw"], "37": ["data\\volunteers\\16M\\Clips\\straightcam\\si456\\38.png", "ah"], "38": ["data\\volunteers\\16M\\Clips\\straightcam\\si456\\39.png", "ah"], "39": ["data\\volunteers\\16M\\Clips\\straightcam\\si456\\40.png", "dh"], "40": ["data\\volunteers\\16M\\Clips\\straightcam\\si456\\41.png", "dh"], "41": ["data\\volunteers\\16M\\Clips\\straightcam\\si456\\42.png", "er"], "42": ["data\\volunteers\\16M\\Clips\\straightcam\\si456\\43.png", "k"], "43": ["data\\volunteers\\16M\\Clips\\straightcam\\si456\\44.png", "k"], "44": ["data\\volunteers\\16M\\Clips\\straightcam\\si456\\45.png", "k"], "45": ["data\\volunteers\\16M\\Clips\\straightcam\\si456\\46.png", "ey"], "46": ["data\\volunteers\\16M\\Clips\\straightcam\\si456\\47.png", "ey"], "47": ["data\\volunteers\\16M\\Clips\\straightcam\\si456\\48.png", "ey"], "48": ["data\\volunteers\\16M\\Clips\\straightcam\\si456\\49.png", "ey"], "49": ["data\\volunteers\\16M\\Clips\\straightcam\\si456\\50.png", "s"], "50": ["data\\volunteers\\16M\\Clips\\straightcam\\si456\\51.png", "s"], "51": ["data\\volunteers\\16M\\Clips\\straightcam\\si456\\52.png", "s"], "52": ["data\\volunteers\\16M\\Clips\\straightcam\\si456\\53.png", "s"], "53": ["data\\volunteers\\16M\\Clips\\straightcam\\si456\\54.png", "ah"], "54": ["data\\volunteers\\16M\\Clips\\straightcam\\si456\\55.png", "z"], "55": ["data\\volunteers\\16M\\Clips\\straightcam\\si456\\56.png", "z"], "56": ["data\\volunteers\\16M\\Clips\\straightcam\\si456\\57.png", "z"], "57": ["data\\volunteers\\16M\\Clips\\straightcam\\si456\\58.png", "z"], "58": ["data\\volunteers\\16M\\Clips\\straightcam\\si456\\59.png", "aa"], "59": ["data\\volunteers\\16M\\Clips\\straightcam\\si456\\60.png", "aa"], "60": ["data\\volunteers\\16M\\Clips\\straightcam\\si456\\61.png", "aa"], "61": ["data\\volunteers\\16M\\Clips\\straightcam\\si456\\62.png", "l"], "62": ["data\\volunteers\\16M\\Clips\\straightcam\\si456\\63.png", "l"], "63": ["data\\volunteers\\16M\\Clips\\straightcam\\si456\\64.png", "s"], "64": ["data\\volunteers\\16M\\Clips\\straightcam\\si456\\65.png", "s"], "65": ["data\\volunteers\\16M\\Clips\\straightcam\\si456\\66.png", "s"], "66": ["data\\volunteers\\16M\\Clips\\straightcam\\si456\\67.png", "ow"], "67": ["data\\volunteers\\16M\\Clips\\straightcam\\si456\\68.png", "ow"], "68": ["data\\volunteers\\16M\\Clips\\straightcam\\si456\\69.png", "ow"], "69": ["data\\volunteers\\16M\\Clips\\straightcam\\si456\\70.png", "w"], "70": ["data\\volunteers\\16M\\Clips\\straightcam\\si456\\71.png", "w"], "71": ["data\\volunteers\\16M\\Clips\\straightcam\\si456\\72.png", "er"], "72": ["data\\volunteers\\16M\\Clips\\straightcam\\si456\\73.png", "er"], "73": ["data\\volunteers\\16M\\Clips\\straightcam\\si456\\74.png", "er"], "74": ["data\\volunteers\\16M\\Clips\\straightcam\\si456\\75.png", "er"], "75": ["data\\volunteers\\16M\\Clips\\straightcam\\si456\\76.png", "ah"], "76": ["data\\volunteers\\16M\\Clips\\straightcam\\si456\\77.png", "ah"], "77": ["data\\volunteers\\16M\\Clips\\straightcam\\si456\\78.png", "n"], "78": ["data\\volunteers\\16M\\Clips\\straightcam\\si456\\79.png", "n"], "79": ["data\\volunteers\\16M\\Clips\\straightcam\\si456\\80.png", "d"], "80": ["data\\volunteers\\16M\\Clips\\straightcam\\si456\\81.png", "er"], "81": ["data\\volunteers\\16M\\Clips\\straightcam\\si456\\82.png", "er"], "82": ["data\\volunteers\\16M\\Clips\\straightcam\\si456\\83.png", "er"], "83": ["data\\volunteers\\16M\\Clips\\straightcam\\si456\\84.png", "er"], "84": ["data\\volunteers\\16M\\Clips\\straightcam\\si456\\85.png", "ah"], "85": ["data\\volunteers\\16M\\Clips\\straightcam\\si456\\86.png", "d"], "86": ["data\\volunteers\\16M\\Clips\\straightcam\\si456\\87.png", "v"], "87": ["data\\volunteers\\16M\\Clips\\straightcam\\si456\\88.png", "ay"], "88": ["data\\volunteers\\16M\\Clips\\straightcam\\si456\\89.png", "ay"], "89": ["data\\volunteers\\16M\\Clips\\straightcam\\si456\\90.png", "ay"], "90": ["data\\volunteers\\16M\\Clips\\straightcam\\si456\\91.png", "ay"], "91": ["data\\volunteers\\16M\\Clips\\straightcam\\si456\\92.png", "ay"], "92": ["data\\volunteers\\16M\\Clips\\straightcam\\si456\\93.png", "z"], "93": ["data\\volunteers\\16M\\Clips\\straightcam\\si456\\94.png", "z"], "94": ["data\\volunteers\\16M\\Clips\\straightcam\\si456\\95.png", "m"], "95": ["data\\volunteers\\16M\\Clips\\straightcam\\si456\\96.png", "ah"], "96": ["data\\volunteers\\16M\\Clips\\straightcam\\si456\\97.png", "n"], "97": ["data\\volunteers\\16M\\Clips\\straightcam\\si456\\98.png", "t"], "98": ["data\\volunteers\\16M\\Clips\\straightcam\\si456\\99.png", "t"]}, "si457": {"30": ["data\\volunteers\\16M\\Clips\\straightcam\\si457\\31.png", "b"], "31": ["data\\volunteers\\16M\\Clips\\straightcam\\si457\\32.png", "b"], "32": ["data\\volunteers\\16M\\Clips\\straightcam\\si457\\33.png", "ow"], "33": ["data\\volunteers\\16M\\Clips\\straightcam\\si457\\34.png", "ow"], "34": ["data\\volunteers\\16M\\Clips\\straightcam\\si457\\35.png", "ow"], "35": ["data\\volunteers\\16M\\Clips\\straightcam\\si457\\36.png", "t"], "36": ["data\\volunteers\\16M\\Clips\\straightcam\\si457\\37.png", "f"], "37": ["data\\volunteers\\16M\\Clips\\straightcam\\si457\\38.png", "f"], "38": ["data\\volunteers\\16M\\Clips\\straightcam\\si457\\39.png", "f"], "39": ["data\\volunteers\\16M\\Clips\\straightcam\\si457\\40.png", "f"], "40": ["data\\volunteers\\16M\\Clips\\straightcam\\si457\\41.png", "ih"], "41": ["data\\volunteers\\16M\\Clips\\straightcam\\si457\\42.png", "g"], "42": ["data\\volunteers\\16M\\Clips\\straightcam\\si457\\43.png", "g"], "43": ["data\\volunteers\\16M\\Clips\\straightcam\\si457\\44.png", "y"], "44": ["data\\volunteers\\16M\\Clips\\straightcam\\si457\\45.png", "er"], "45": ["data\\volunteers\\16M\\Clips\\straightcam\\si457\\46.png", "z"], "46": ["data\\volunteers\\16M\\Clips\\straightcam\\si457\\47.png", "z"], "47": ["data\\volunteers\\16M\\Clips\\straightcam\\si457\\48.png", "z"], "48": ["data\\volunteers\\16M\\Clips\\straightcam\\si457\\49.png", "w"], "49": ["data\\volunteers\\16M\\Clips\\straightcam\\si457\\50.png", "uh"], "50": ["data\\volunteers\\16M\\Clips\\straightcam\\si457\\51.png", "d"], "51": ["data\\volunteers\\16M\\Clips\\straightcam\\si457\\52.png", "g"], "52": ["data\\volunteers\\16M\\Clips\\straightcam\\si457\\53.png", "ow"], "53": ["data\\volunteers\\16M\\Clips\\straightcam\\si457\\54.png", "ow"], "54": ["data\\volunteers\\16M\\Clips\\straightcam\\si457\\55.png", "ow"], "55": ["data\\volunteers\\16M\\Clips\\straightcam\\si457\\56.png", "ow"], "56": ["data\\volunteers\\16M\\Clips\\straightcam\\si457\\57.png", "hh"], "57": ["data\\volunteers\\16M\\Clips\\straightcam\\si457\\58.png", "hh"], "58": ["data\\volunteers\\16M\\Clips\\straightcam\\si457\\59.png", "hh"], "59": ["data\\volunteers\\16M\\Clips\\straightcam\\si457\\60.png", "ay"], "60": ["data\\volunteers\\16M\\Clips\\straightcam\\si457\\61.png", "ay"], "61": ["data\\volunteers\\16M\\Clips\\straightcam\\si457\\62.png", "ay"], "62": ["data\\volunteers\\16M\\Clips\\straightcam\\si457\\63.png", "ay"], "63": ["data\\volunteers\\16M\\Clips\\straightcam\\si457\\64.png", "ay"], "64": ["data\\volunteers\\16M\\Clips\\straightcam\\si457\\65.png", "er"], "65": ["data\\volunteers\\16M\\Clips\\straightcam\\si457\\66.png", "er"], "66": ["data\\volunteers\\16M\\Clips\\straightcam\\si457\\67.png", "ah"], "67": ["data\\volunteers\\16M\\Clips\\straightcam\\si457\\68.png", "n"], "68": ["data\\volunteers\\16M\\Clips\\straightcam\\si457\\69.png", "n"], "69": ["data\\volunteers\\16M\\Clips\\straightcam\\si457\\70.png", "l"], "70": ["data\\volunteers\\16M\\Clips\\straightcam\\si457\\71.png", "l"], "71": ["data\\volunteers\\16M\\Clips\\straightcam\\si457\\72.png", "ey"], "72": ["data\\volunteers\\16M\\Clips\\straightcam\\si457\\73.png", "ey"], "73": ["data\\volunteers\\16M\\Clips\\straightcam\\si457\\74.png", "ey"], "74": ["data\\volunteers\\16M\\Clips\\straightcam\\si457\\75.png", "t"], "75": ["data\\volunteers\\16M\\Clips\\straightcam\\si457\\76.png", "er"], "76": ["data\\volunteers\\16M\\Clips\\straightcam\\si457\\77.png", "er"], "77": ["data\\volunteers\\16M\\Clips\\straightcam\\si457\\78.png", "y"], "78": ["data\\volunteers\\16M\\Clips\\straightcam\\si457\\79.png", "y"], "79": ["data\\volunteers\\16M\\Clips\\straightcam\\si457\\80.png", "y"], "80": ["data\\volunteers\\16M\\Clips\\straightcam\\si457\\81.png", "y"], "81": ["data\\volunteers\\16M\\Clips\\straightcam\\si457\\82.png", "y"], "82": ["data\\volunteers\\16M\\Clips\\straightcam\\si457\\83.png", "er"], "83": ["data\\volunteers\\16M\\Clips\\straightcam\\si457\\84.png", "er"], "84": ["data\\volunteers\\16M\\Clips\\straightcam\\si457\\85.png", "er"], "85": ["data\\volunteers\\16M\\Clips\\straightcam\\si457\\86.png", "z"], "86": ["data\\volunteers\\16M\\Clips\\straightcam\\si457\\87.png", "z"], "87": ["data\\volunteers\\16M\\Clips\\straightcam\\si457\\88.png", "z"], "88": ["data\\volunteers\\16M\\Clips\\straightcam\\si457\\89.png", "z"], "89": ["data\\volunteers\\16M\\Clips\\straightcam\\si457\\90.png", "z"], "90": ["data\\volunteers\\16M\\Clips\\straightcam\\si457\\91.png", "z"], "91": ["data\\volunteers\\16M\\Clips\\straightcam\\si457\\92.png", "z"]}, "si458": {"30": ["data\\volunteers\\16M\\Clips\\straightcam\\si458\\31.png", "dh"], "31": ["data\\volunteers\\16M\\Clips\\straightcam\\si458\\32.png", "ih"], "32": ["data\\volunteers\\16M\\Clips\\straightcam\\si458\\33.png", "ih"], "33": ["data\\volunteers\\16M\\Clips\\straightcam\\si458\\34.png", "s"], "34": ["data\\volunteers\\16M\\Clips\\straightcam\\si458\\35.png", "ah"], "35": ["data\\volunteers\\16M\\Clips\\straightcam\\si458\\36.png", "z"], "36": ["data\\volunteers\\16M\\Clips\\straightcam\\si458\\37.png", "n"], "37": ["data\\volunteers\\16M\\Clips\\straightcam\\si458\\38.png", "n"], "38": ["data\\volunteers\\16M\\Clips\\straightcam\\si458\\39.png", "aa"], "39": ["data\\volunteers\\16M\\Clips\\straightcam\\si458\\40.png", "aa"], "40": ["data\\volunteers\\16M\\Clips\\straightcam\\si458\\41.png", "aa"], "41": ["data\\volunteers\\16M\\Clips\\straightcam\\si458\\42.png", "t"], "42": ["data\\volunteers\\16M\\Clips\\straightcam\\si458\\43.png", "ah"], "43": ["data\\volunteers\\16M\\Clips\\straightcam\\si458\\44.png", "p"], "44": ["data\\volunteers\\16M\\Clips\\straightcam\\si458\\45.png", "p"], "45": ["data\\volunteers\\16M\\Clips\\straightcam\\si458\\46.png", "r"], "46": ["data\\volunteers\\16M\\Clips\\straightcam\\si458\\47.png", "r"], "47": ["data\\volunteers\\16M\\Clips\\straightcam\\si458\\48.png", "r"], "48": ["data\\volunteers\\16M\\Clips\\straightcam\\si458\\49.png", "r"], "49": ["data\\volunteers\\16M\\Clips\\straightcam\\si458\\50.png", "ow"], "50": ["data\\volunteers\\16M\\Clips\\straightcam\\si458\\51.png", "g"], "51": ["data\\volunteers\\16M\\Clips\\straightcam\\si458\\52.png", "g"], "52": ["data\\volunteers\\16M\\Clips\\straightcam\\si458\\53.png", "r"], "53": ["data\\volunteers\\16M\\Clips\\straightcam\\si458\\54.png", "ae"], "54": ["data\\volunteers\\16M\\Clips\\straightcam\\si458\\55.png", "m"], "55": ["data\\volunteers\\16M\\Clips\\straightcam\\si458\\56.png", "m"], "56": ["data\\volunteers\\16M\\Clips\\straightcam\\si458\\57.png", "ah"], "57": ["data\\volunteers\\16M\\Clips\\straightcam\\si458\\58.png", "s"], "58": ["data\\volunteers\\16M\\Clips\\straightcam\\si458\\59.png", "s"], "59": ["data\\volunteers\\16M\\Clips\\straightcam\\si458\\60.png", "s"], "60": ["data\\volunteers\\16M\\Clips\\straightcam\\si458\\61.png", "s"], "61": ["data\\volunteers\\16M\\Clips\\straightcam\\si458\\62.png", "ow"], "62": ["data\\volunteers\\16M\\Clips\\straightcam\\si458\\63.png", "ow"], "63": ["data\\volunteers\\16M\\Clips\\straightcam\\si458\\64.png", "sh"], "64": ["data\\volunteers\\16M\\Clips\\straightcam\\si458\\65.png", "sh"], "65": ["data\\volunteers\\16M\\Clips\\straightcam\\si458\\66.png", "sh"], "66": ["data\\volunteers\\16M\\Clips\\straightcam\\si458\\67.png", "sh"], "67": ["data\\volunteers\\16M\\Clips\\straightcam\\si458\\68.png", "ah"], "68": ["data\\volunteers\\16M\\Clips\\straightcam\\si458\\69.png", "l"], "69": ["data\\volunteers\\16M\\Clips\\straightcam\\si458\\70.png", "ay"], "70": ["data\\volunteers\\16M\\Clips\\straightcam\\si458\\71.png", "ay"], "71": ["data\\volunteers\\16M\\Clips\\straightcam\\si458\\72.png", "ay"], "72": ["data\\volunteers\\16M\\Clips\\straightcam\\si458\\73.png", "z"], "73": ["data\\volunteers\\16M\\Clips\\straightcam\\si458\\74.png", "z"], "74": ["data\\volunteers\\16M\\Clips\\straightcam\\si458\\75.png", "z"], "75": ["data\\volunteers\\16M\\Clips\\straightcam\\si458\\76.png", "d"], "76": ["data\\volunteers\\16M\\Clips\\straightcam\\si458\\77.png", "m"], "77": ["data\\volunteers\\16M\\Clips\\straightcam\\si458\\78.png", "eh"], "78": ["data\\volunteers\\16M\\Clips\\straightcam\\si458\\79.png", "eh"], "79": ["data\\volunteers\\16M\\Clips\\straightcam\\si458\\80.png", "d"], "80": ["data\\volunteers\\16M\\Clips\\straightcam\\si458\\81.png", "ah"], "81": ["data\\volunteers\\16M\\Clips\\straightcam\\si458\\82.png", "s"], "82": ["data\\volunteers\\16M\\Clips\\straightcam\\si458\\83.png", "s"], "83": ["data\\volunteers\\16M\\Clips\\straightcam\\si458\\84.png", "s"], "84": ["data\\volunteers\\16M\\Clips\\straightcam\\si458\\85.png", "ah"], "85": ["data\\volunteers\\16M\\Clips\\straightcam\\si458\\86.png", "n"], "86": ["data\\volunteers\\16M\\Clips\\straightcam\\si458\\87.png", "n"], "87": ["data\\volunteers\\16M\\Clips\\straightcam\\si458\\88.png", "n"]}, "si460": {"30": ["data\\volunteers\\16M\\Clips\\straightcam\\si460\\31.png", "n"], "31": ["data\\volunteers\\16M\\Clips\\straightcam\\si460\\32.png", "n"], "32": ["data\\volunteers\\16M\\Clips\\straightcam\\si460\\33.png", "n"], "33": ["data\\volunteers\\16M\\Clips\\straightcam\\si460\\34.png", "ah"], "34": ["data\\volunteers\\16M\\Clips\\straightcam\\si460\\35.png", "ah"], "35": ["data\\volunteers\\16M\\Clips\\straightcam\\si460\\36.png", "th"], "36": ["data\\volunteers\\16M\\Clips\\straightcam\\si460\\37.png", "th"], "37": ["data\\volunteers\\16M\\Clips\\straightcam\\si460\\38.png", "th"], "38": ["data\\volunteers\\16M\\Clips\\straightcam\\si460\\39.png", "ih"], "39": ["data\\volunteers\\16M\\Clips\\straightcam\\si460\\40.png", "ng"], "40": ["data\\volunteers\\16M\\Clips\\straightcam\\si460\\41.png", "ng"], "41": ["data\\volunteers\\16M\\Clips\\straightcam\\si460\\42.png", "hh"], "42": ["data\\volunteers\\16M\\Clips\\straightcam\\si460\\43.png", "ah"], "43": ["data\\volunteers\\16M\\Clips\\straightcam\\si460\\44.png", "z"], "44": ["data\\volunteers\\16M\\Clips\\straightcam\\si460\\45.png", "z"], "45": ["data\\volunteers\\16M\\Clips\\straightcam\\si460\\46.png", "b"], "46": ["data\\volunteers\\16M\\Clips\\straightcam\\si460\\47.png", "b"], "47": ["data\\volunteers\\16M\\Clips\\straightcam\\si460\\48.png", "ah"], "48": ["data\\volunteers\\16M\\Clips\\straightcam\\si460\\49.png", "n"], "49": ["data\\volunteers\\16M\\Clips\\straightcam\\si460\\50.png", "d"], "50": ["data\\volunteers\\16M\\Clips\\straightcam\\si460\\51.png", "d"], "51": ["data\\volunteers\\16M\\Clips\\straightcam\\si460\\52.png", "ah"], "52": ["data\\volunteers\\16M\\Clips\\straightcam\\si460\\53.png", "ah"], "53": ["data\\volunteers\\16M\\Clips\\straightcam\\si460\\54.png", "ah"], "54": ["data\\volunteers\\16M\\Clips\\straightcam\\si460\\55.png", "n"], "55": ["data\\volunteers\\16M\\Clips\\straightcam\\si460\\56.png", "n"], "56": ["data\\volunteers\\16M\\Clips\\straightcam\\si460\\57.png", "y"], "57": ["data\\volunteers\\16M\\Clips\\straightcam\\si460\\58.png", "y"], "58": ["data\\volunteers\\16M\\Clips\\straightcam\\si460\\59.png", "eh"], "59": ["data\\volunteers\\16M\\Clips\\straightcam\\si460\\60.png", "eh"], "60": ["data\\volunteers\\16M\\Clips\\straightcam\\si460\\61.png", "eh"], "61": ["data\\volunteers\\16M\\Clips\\straightcam\\si460\\62.png", "t"], "64": ["data\\volunteers\\16M\\Clips\\straightcam\\si460\\65.png", "t"], "65": ["data\\volunteers\\16M\\Clips\\straightcam\\si460\\66.png", "t"], "66": ["data\\volunteers\\16M\\Clips\\straightcam\\si460\\67.png", "ih"], "67": ["data\\volunteers\\16M\\Clips\\straightcam\\si460\\68.png", "t"], "68": ["data\\volunteers\\16M\\Clips\\straightcam\\si460\\69.png", "t"], "69": ["data\\volunteers\\16M\\Clips\\straightcam\\si460\\70.png", "t"], "70": ["data\\volunteers\\16M\\Clips\\straightcam\\si460\\71.png", "ey"], "71": ["data\\volunteers\\16M\\Clips\\straightcam\\si460\\72.png", "ey"], "72": ["data\\volunteers\\16M\\Clips\\straightcam\\si460\\73.png", "k"], "73": ["data\\volunteers\\16M\\Clips\\straightcam\\si460\\74.png", "k"], "74": ["data\\volunteers\\16M\\Clips\\straightcam\\si460\\75.png", "ah"], "75": ["data\\volunteers\\16M\\Clips\\straightcam\\si460\\76.png", "d"], "76": ["data\\volunteers\\16M\\Clips\\straightcam\\si460\\77.png", "v"], "77": ["data\\volunteers\\16M\\Clips\\straightcam\\si460\\78.png", "ae"], "78": ["data\\volunteers\\16M\\Clips\\straightcam\\si460\\79.png", "ae"], "79": ["data\\volunteers\\16M\\Clips\\straightcam\\si460\\80.png", "ae"], "80": ["data\\volunteers\\16M\\Clips\\straightcam\\si460\\81.png", "ae"], "81": ["data\\volunteers\\16M\\Clips\\straightcam\\si460\\82.png", "n"], "82": ["data\\volunteers\\16M\\Clips\\straightcam\\si460\\83.png", "t"], "83": ["data\\volunteers\\16M\\Clips\\straightcam\\si460\\84.png", "t"], "84": ["data\\volunteers\\16M\\Clips\\straightcam\\si460\\85.png", "ih"], "85": ["data\\volunteers\\16M\\Clips\\straightcam\\si460\\86.png", "jh"], "86": ["data\\volunteers\\16M\\Clips\\straightcam\\si460\\87.png", "jh"], "87": ["data\\volunteers\\16M\\Clips\\straightcam\\si460\\88.png", "jh"], "88": ["data\\volunteers\\16M\\Clips\\straightcam\\si460\\89.png", "ah"], "89": ["data\\volunteers\\16M\\Clips\\straightcam\\si460\\90.png", "ah"], "90": ["data\\volunteers\\16M\\Clips\\straightcam\\si460\\91.png", "v"], "91": ["data\\volunteers\\16M\\Clips\\straightcam\\si460\\92.png", "v"], "92": ["data\\volunteers\\16M\\Clips\\straightcam\\si460\\93.png", "dh"], "93": ["data\\volunteers\\16M\\Clips\\straightcam\\si460\\94.png", "ah"], "94": ["data\\volunteers\\16M\\Clips\\straightcam\\si460\\95.png", "eh"], "95": ["data\\volunteers\\16M\\Clips\\straightcam\\si460\\96.png", "n"], "96": ["data\\volunteers\\16M\\Clips\\straightcam\\si460\\97.png", "n"], "97": ["data\\volunteers\\16M\\Clips\\straightcam\\si460\\98.png", "ey"], "98": ["data\\volunteers\\16M\\Clips\\straightcam\\si460\\99.png", "ey"], "99": ["data\\volunteers\\16M\\Clips\\straightcam\\si460\\100.png", "ey"], "100": ["data\\volunteers\\16M\\Clips\\straightcam\\si460\\101.png", "ey"], "101": ["data\\volunteers\\16M\\Clips\\straightcam\\si460\\102.png", "b"], "102": ["data\\volunteers\\16M\\Clips\\straightcam\\si460\\103.png", "b"], "103": ["data\\volunteers\\16M\\Clips\\straightcam\\si460\\104.png", "ah"], "104": ["data\\volunteers\\16M\\Clips\\straightcam\\si460\\105.png", "l"], "105": ["data\\volunteers\\16M\\Clips\\straightcam\\si460\\106.png", "ih"], "106": ["data\\volunteers\\16M\\Clips\\straightcam\\si460\\107.png", "ng"], "107": ["data\\volunteers\\16M\\Clips\\straightcam\\si460\\108.png", "ng"], "108": ["data\\volunteers\\16M\\Clips\\straightcam\\si460\\109.png", "ng"], "109": ["data\\volunteers\\16M\\Clips\\straightcam\\si460\\110.png", "ng"], "110": ["data\\volunteers\\16M\\Clips\\straightcam\\si460\\111.png", "ng"], "111": ["data\\volunteers\\16M\\Clips\\straightcam\\si460\\112.png", "ng"], "112": ["data\\volunteers\\16M\\Clips\\straightcam\\si460\\113.png", "l"], "113": ["data\\volunteers\\16M\\Clips\\straightcam\\si460\\114.png", "l"], "114": ["data\\volunteers\\16M\\Clips\\straightcam\\si460\\115.png", "eh"], "115": ["data\\volunteers\\16M\\Clips\\straightcam\\si460\\116.png", "eh"], "116": ["data\\volunteers\\16M\\Clips\\straightcam\\si460\\117.png", "eh"], "117": ["data\\volunteers\\16M\\Clips\\straightcam\\si460\\118.png", "jh"], "118": ["data\\volunteers\\16M\\Clips\\straightcam\\si460\\119.png", "jh"], "119": ["data\\volunteers\\16M\\Clips\\straightcam\\si460\\120.png", "ah"], "120": ["data\\volunteers\\16M\\Clips\\straightcam\\si460\\121.png", "s"], "121": ["data\\volunteers\\16M\\Clips\\straightcam\\si460\\122.png", "s"], "122": ["data\\volunteers\\16M\\Clips\\straightcam\\si460\\123.png", "s"], "123": ["data\\volunteers\\16M\\Clips\\straightcam\\si460\\124.png", "s"], "124": ["data\\volunteers\\16M\\Clips\\straightcam\\si460\\125.png", "l"], "125": ["data\\volunteers\\16M\\Clips\\straightcam\\si460\\126.png", "ey"], "126": ["data\\volunteers\\16M\\Clips\\straightcam\\si460\\127.png", "ey"], "127": ["data\\volunteers\\16M\\Clips\\straightcam\\si460\\128.png", "sh"], "128": ["data\\volunteers\\16M\\Clips\\straightcam\\si460\\129.png", "sh"], "129": ["data\\volunteers\\16M\\Clips\\straightcam\\si460\\130.png", "sh"], "130": ["data\\volunteers\\16M\\Clips\\straightcam\\si460\\131.png", "sh"], "131": ["data\\volunteers\\16M\\Clips\\straightcam\\si460\\132.png", "ah"], "132": ["data\\volunteers\\16M\\Clips\\straightcam\\si460\\133.png", "n"], "133": ["data\\volunteers\\16M\\Clips\\straightcam\\si460\\134.png", "n"]}, "si525": {"30": ["data\\volunteers\\16M\\Clips\\straightcam\\si525\\31.png", "dh"], "31": ["data\\volunteers\\16M\\Clips\\straightcam\\si525\\32.png", "dh"], "32": ["data\\volunteers\\16M\\Clips\\straightcam\\si525\\33.png", "dh"], "33": ["data\\volunteers\\16M\\Clips\\straightcam\\si525\\34.png", "ah"], "34": ["data\\volunteers\\16M\\Clips\\straightcam\\si525\\35.png", "d"], "35": ["data\\volunteers\\16M\\Clips\\straightcam\\si525\\36.png", "d"], "36": ["data\\volunteers\\16M\\Clips\\straightcam\\si525\\37.png", "ah"], "37": ["data\\volunteers\\16M\\Clips\\straightcam\\si525\\38.png", "ah"], "38": ["data\\volunteers\\16M\\Clips\\straightcam\\si525\\39.png", "z"], "39": ["data\\volunteers\\16M\\Clips\\straightcam\\si525\\40.png", "z"], "40": ["data\\volunteers\\16M\\Clips\\straightcam\\si525\\41.png", "ay"], "41": ["data\\volunteers\\16M\\Clips\\straightcam\\si525\\42.png", "ay"], "42": ["data\\volunteers\\16M\\Clips\\straightcam\\si525\\43.png", "ay"], "43": ["data\\volunteers\\16M\\Clips\\straightcam\\si525\\44.png", "ay"], "44": ["data\\volunteers\\16M\\Clips\\straightcam\\si525\\45.png", "ay"], "45": ["data\\volunteers\\16M\\Clips\\straightcam\\si525\\46.png", "er"], "46": ["data\\volunteers\\16M\\Clips\\straightcam\\si525\\47.png", "ae"], "47": ["data\\volunteers\\16M\\Clips\\straightcam\\si525\\48.png", "n"], "48": ["data\\volunteers\\16M\\Clips\\straightcam\\si525\\49.png", "d"], "49": ["data\\volunteers\\16M\\Clips\\straightcam\\si525\\50.png", "ah"], "50": ["data\\volunteers\\16M\\Clips\\straightcam\\si525\\51.png", "ah"], "51": ["data\\volunteers\\16M\\Clips\\straightcam\\si525\\52.png", "b"], "52": ["data\\volunteers\\16M\\Clips\\straightcam\\si525\\53.png", "b"], "53": ["data\\volunteers\\16M\\Clips\\straightcam\\si525\\54.png", "ih"], "54": ["data\\volunteers\\16M\\Clips\\straightcam\\si525\\55.png", "ih"], "55": ["data\\volunteers\\16M\\Clips\\straightcam\\si525\\56.png", "ih"], "56": ["data\\volunteers\\16M\\Clips\\straightcam\\si525\\57.png", "l"], "57": ["data\\volunteers\\16M\\Clips\\straightcam\\si525\\58.png", "ah"], "58": ["data\\volunteers\\16M\\Clips\\straightcam\\si525\\59.png", "t"], "59": ["data\\volunteers\\16M\\Clips\\straightcam\\si525\\60.png", "t"], "60": ["data\\volunteers\\16M\\Clips\\straightcam\\si525\\61.png", "t"], "61": ["data\\volunteers\\16M\\Clips\\straightcam\\si525\\62.png", "iy"], "62": ["data\\volunteers\\16M\\Clips\\straightcam\\si525\\63.png", "iy"], "63": ["data\\volunteers\\16M\\Clips\\straightcam\\si525\\64.png", "t"], "64": ["data\\volunteers\\16M\\Clips\\straightcam\\si525\\65.png", "t"], "65": ["data\\volunteers\\16M\\Clips\\straightcam\\si525\\66.png", "uw"], "66": ["data\\volunteers\\16M\\Clips\\straightcam\\si525\\67.png", "uw"], "67": ["data\\volunteers\\16M\\Clips\\straightcam\\si525\\68.png", "uw"], "68": ["data\\volunteers\\16M\\Clips\\straightcam\\si525\\69.png", "r"], "69": ["data\\volunteers\\16M\\Clips\\straightcam\\si525\\70.png", "r"], "70": ["data\\volunteers\\16M\\Clips\\straightcam\\si525\\71.png", "iy"], "71": ["data\\volunteers\\16M\\Clips\\straightcam\\si525\\72.png", "iy"], "72": ["data\\volunteers\\16M\\Clips\\straightcam\\si525\\73.png", "iy"], "73": ["data\\volunteers\\16M\\Clips\\straightcam\\si525\\74.png", "iy"], "74": ["data\\volunteers\\16M\\Clips\\straightcam\\si525\\75.png", "iy"], "75": ["data\\volunteers\\16M\\Clips\\straightcam\\si525\\76.png", "iy"], "76": ["data\\volunteers\\16M\\Clips\\straightcam\\si525\\77.png", "d"], "77": ["data\\volunteers\\16M\\Clips\\straightcam\\si525\\78.png", "d"], "78": ["data\\volunteers\\16M\\Clips\\straightcam\\si525\\79.png", "d"], "79": ["data\\volunteers\\16M\\Clips\\straightcam\\si525\\80.png", "d"], "80": ["data\\volunteers\\16M\\Clips\\straightcam\\si525\\81.png", "aa"], "81": ["data\\volunteers\\16M\\Clips\\straightcam\\si525\\82.png", "aa"], "82": ["data\\volunteers\\16M\\Clips\\straightcam\\si525\\83.png", "aa"], "83": ["data\\volunteers\\16M\\Clips\\straightcam\\si525\\84.png", "aa"], "84": ["data\\volunteers\\16M\\Clips\\straightcam\\si525\\85.png", "r"], "85": ["data\\volunteers\\16M\\Clips\\straightcam\\si525\\86.png", "r"], "86": ["data\\volunteers\\16M\\Clips\\straightcam\\si525\\87.png", "ih"], "87": ["data\\volunteers\\16M\\Clips\\straightcam\\si525\\88.png", "p"], "88": ["data\\volunteers\\16M\\Clips\\straightcam\\si525\\89.png", "p"], "89": ["data\\volunteers\\16M\\Clips\\straightcam\\si525\\90.png", "aa"], "90": ["data\\volunteers\\16M\\Clips\\straightcam\\si525\\91.png", "aa"], "91": ["data\\volunteers\\16M\\Clips\\straightcam\\si525\\92.png", "aa"], "92": ["data\\volunteers\\16M\\Clips\\straightcam\\si525\\93.png", "r"], "93": ["data\\volunteers\\16M\\Clips\\straightcam\\si525\\94.png", "t"], "94": ["data\\volunteers\\16M\\Clips\\straightcam\\si525\\95.png", "ah"], "95": ["data\\volunteers\\16M\\Clips\\straightcam\\si525\\96.png", "n"], "96": ["data\\volunteers\\16M\\Clips\\straightcam\\si525\\97.png", "t"], "97": ["data\\volunteers\\16M\\Clips\\straightcam\\si525\\98.png", "ae"], "98": ["data\\volunteers\\16M\\Clips\\straightcam\\si525\\99.png", "ae"], "99": ["data\\volunteers\\16M\\Clips\\straightcam\\si525\\100.png", "ae"], "100": ["data\\volunteers\\16M\\Clips\\straightcam\\si525\\101.png", "ae"], "101": ["data\\volunteers\\16M\\Clips\\straightcam\\si525\\102.png", "s"], "102": ["data\\volunteers\\16M\\Clips\\straightcam\\si525\\103.png", "s"], "103": ["data\\volunteers\\16M\\Clips\\straightcam\\si525\\104.png", "s"], "104": ["data\\volunteers\\16M\\Clips\\straightcam\\si525\\105.png", "p"], "105": ["data\\volunteers\\16M\\Clips\\straightcam\\si525\\106.png", "eh"], "106": ["data\\volunteers\\16M\\Clips\\straightcam\\si525\\107.png", "eh"], "107": ["data\\volunteers\\16M\\Clips\\straightcam\\si525\\108.png", "k"], "108": ["data\\volunteers\\16M\\Clips\\straightcam\\si525\\109.png", "t"], "109": ["data\\volunteers\\16M\\Clips\\straightcam\\si525\\110.png", "s"], "110": ["data\\volunteers\\16M\\Clips\\straightcam\\si525\\111.png", "s"], "111": ["data\\volunteers\\16M\\Clips\\straightcam\\si525\\112.png", "s"], "112": ["data\\volunteers\\16M\\Clips\\straightcam\\si525\\113.png", "s"], "113": ["data\\volunteers\\16M\\Clips\\straightcam\\si525\\114.png", "ah"], "114": ["data\\volunteers\\16M\\Clips\\straightcam\\si525\\115.png", "ah"], "115": ["data\\volunteers\\16M\\Clips\\straightcam\\si525\\116.png", "v"], "116": ["data\\volunteers\\16M\\Clips\\straightcam\\si525\\117.png", "aa"], "117": ["data\\volunteers\\16M\\Clips\\straightcam\\si525\\118.png", "r"], "118": ["data\\volunteers\\16M\\Clips\\straightcam\\si525\\119.png", "r"], "119": ["data\\volunteers\\16M\\Clips\\straightcam\\si525\\120.png", "r"], "120": ["data\\volunteers\\16M\\Clips\\straightcam\\si525\\121.png", "k"], "121": ["data\\volunteers\\16M\\Clips\\straightcam\\si525\\122.png", "k"], "122": ["data\\volunteers\\16M\\Clips\\straightcam\\si525\\123.png", "k"], "123": ["data\\volunteers\\16M\\Clips\\straightcam\\si525\\124.png", "ah"], "124": ["data\\volunteers\\16M\\Clips\\straightcam\\si525\\125.png", "l"], "125": ["data\\volunteers\\16M\\Clips\\straightcam\\si525\\126.png", "l"], "126": ["data\\volunteers\\16M\\Clips\\straightcam\\si525\\127.png", "ch"], "127": ["data\\volunteers\\16M\\Clips\\straightcam\\si525\\128.png", "ch"], "128": ["data\\volunteers\\16M\\Clips\\straightcam\\si525\\129.png", "ch"], "129": ["data\\volunteers\\16M\\Clips\\straightcam\\si525\\130.png", "er"], "130": ["data\\volunteers\\16M\\Clips\\straightcam\\si525\\131.png", "er"], "131": ["data\\volunteers\\16M\\Clips\\straightcam\\si525\\132.png", "er"], "132": ["data\\volunteers\\16M\\Clips\\straightcam\\si525\\133.png", "ah"], "133": ["data\\volunteers\\16M\\Clips\\straightcam\\si525\\134.png", "l"], "134": ["data\\volunteers\\16M\\Clips\\straightcam\\si525\\135.png", "l"], "135": ["data\\volunteers\\16M\\Clips\\straightcam\\si525\\136.png", "l"], "136": ["data\\volunteers\\16M\\Clips\\straightcam\\si525\\137.png", "l"], "137": ["data\\volunteers\\16M\\Clips\\straightcam\\si525\\138.png", "ay"], "138": ["data\\volunteers\\16M\\Clips\\straightcam\\si525\\139.png", "ay"], "139": ["data\\volunteers\\16M\\Clips\\straightcam\\si525\\140.png", "ay"], "140": ["data\\volunteers\\16M\\Clips\\straightcam\\si525\\141.png", "f"], "141": ["data\\volunteers\\16M\\Clips\\straightcam\\si525\\142.png", "f"], "142": ["data\\volunteers\\16M\\Clips\\straightcam\\si525\\143.png", "f"], "143": ["data\\volunteers\\16M\\Clips\\straightcam\\si525\\144.png", "f"], "144": ["data\\volunteers\\16M\\Clips\\straightcam\\si525\\145.png", "f"], "145": ["data\\volunteers\\16M\\Clips\\straightcam\\si525\\146.png", "f"], "146": ["data\\volunteers\\16M\\Clips\\straightcam\\si525\\147.png", "f"]}, "si551": {"30": ["data\\volunteers\\16M\\Clips\\straightcam\\si551\\31.png", "ih"], "31": ["data\\volunteers\\16M\\Clips\\straightcam\\si551\\32.png", "ih"], "32": ["data\\volunteers\\16M\\Clips\\straightcam\\si551\\33.png", "ih"], "33": ["data\\volunteers\\16M\\Clips\\straightcam\\si551\\34.png", "z"], "34": ["data\\volunteers\\16M\\Clips\\straightcam\\si551\\35.png", "d"], "35": ["data\\volunteers\\16M\\Clips\\straightcam\\si551\\36.png", "d"], "36": ["data\\volunteers\\16M\\Clips\\straightcam\\si551\\37.png", "ah"], "37": ["data\\volunteers\\16M\\Clips\\straightcam\\si551\\38.png", "m"], "38": ["data\\volunteers\\16M\\Clips\\straightcam\\si551\\39.png", "m"], "39": ["data\\volunteers\\16M\\Clips\\straightcam\\si551\\40.png", "m"], "40": ["data\\volunteers\\16M\\Clips\\straightcam\\si551\\41.png", "ah"], "41": ["data\\volunteers\\16M\\Clips\\straightcam\\si551\\42.png", "ah"], "42": ["data\\volunteers\\16M\\Clips\\straightcam\\si551\\43.png", "d"], "43": ["data\\volunteers\\16M\\Clips\\straightcam\\si551\\44.png", "er"], "44": ["data\\volunteers\\16M\\Clips\\straightcam\\si551\\45.png", "er"], "45": ["data\\volunteers\\16M\\Clips\\straightcam\\si551\\46.png", "er"], "46": ["data\\volunteers\\16M\\Clips\\straightcam\\si551\\47.png", "ah"], "47": ["data\\volunteers\\16M\\Clips\\straightcam\\si551\\48.png", "v"], "48": ["data\\volunteers\\16M\\Clips\\straightcam\\si551\\49.png", "ah"], "49": ["data\\volunteers\\16M\\Clips\\straightcam\\si551\\50.png", "n"], "50": ["data\\volunteers\\16M\\Clips\\straightcam\\si551\\51.png", "n"], "51": ["data\\volunteers\\16M\\Clips\\straightcam\\si551\\52.png", "aa"], "52": ["data\\volunteers\\16M\\Clips\\straightcam\\si551\\53.png", "t"], "53": ["data\\volunteers\\16M\\Clips\\straightcam\\si551\\54.png", "t"], "54": ["data\\volunteers\\16M\\Clips\\straightcam\\si551\\55.png", "t"], "55": ["data\\volunteers\\16M\\Clips\\straightcam\\si551\\56.png", "t"], "56": ["data\\volunteers\\16M\\Clips\\straightcam\\si551\\57.png", "t"], "57": ["data\\volunteers\\16M\\Clips\\straightcam\\si551\\58.png", "ih"], "58": ["data\\volunteers\\16M\\Clips\\straightcam\\si551\\59.png", "s"], "59": ["data\\volunteers\\16M\\Clips\\straightcam\\si551\\60.png", "s"], "60": ["data\\volunteers\\16M\\Clips\\straightcam\\si551\\61.png", "t"], "61": ["data\\volunteers\\16M\\Clips\\straightcam\\si551\\62.png", "ih"], "62": ["data\\volunteers\\16M\\Clips\\straightcam\\si551\\63.png", "ih"], "63": ["data\\volunteers\\16M\\Clips\\straightcam\\si551\\64.png", "k"], "64": ["data\\volunteers\\16M\\Clips\\straightcam\\si551\\65.png", "ch"], "65": ["data\\volunteers\\16M\\Clips\\straightcam\\si551\\66.png", "ch"], "66": ["data\\volunteers\\16M\\Clips\\straightcam\\si551\\67.png", "ch"], "67": ["data\\volunteers\\16M\\Clips\\straightcam\\si551\\68.png", "ch"], "68": ["data\\volunteers\\16M\\Clips\\straightcam\\si551\\69.png", "ay"], "69": ["data\\volunteers\\16M\\Clips\\straightcam\\si551\\70.png", "ay"], "70": ["data\\volunteers\\16M\\Clips\\straightcam\\si551\\71.png", "ay"], "71": ["data\\volunteers\\16M\\Clips\\straightcam\\si551\\72.png", "ay"], "72": ["data\\volunteers\\16M\\Clips\\straightcam\\si551\\73.png", "ay"], "73": ["data\\volunteers\\16M\\Clips\\straightcam\\si551\\74.png", "ay"], "74": ["data\\volunteers\\16M\\Clips\\straightcam\\si551\\75.png", "l"], "75": ["data\\volunteers\\16M\\Clips\\straightcam\\si551\\76.png", "d"], "76": ["data\\volunteers\\16M\\Clips\\straightcam\\si551\\77.png", "ae"], "77": ["data\\volunteers\\16M\\Clips\\straightcam\\si551\\78.png", "ah"], "78": ["data\\volunteers\\16M\\Clips\\straightcam\\si551\\79.png", "f"], "79": ["data\\volunteers\\16M\\Clips\\straightcam\\si551\\80.png", "f"], "80": ["data\\volunteers\\16M\\Clips\\straightcam\\si551\\81.png", "f"], "81": ["data\\volunteers\\16M\\Clips\\straightcam\\si551\\82.png", "f"], "82": ["data\\volunteers\\16M\\Clips\\straightcam\\si551\\83.png", "aa"], "83": ["data\\volunteers\\16M\\Clips\\straightcam\\si551\\84.png", "aa"], "84": ["data\\volunteers\\16M\\Clips\\straightcam\\si551\\85.png", "aa"], "85": ["data\\volunteers\\16M\\Clips\\straightcam\\si551\\86.png", "l"], "86": ["data\\volunteers\\16M\\Clips\\straightcam\\si551\\87.png", "l"], "87": ["data\\volunteers\\16M\\Clips\\straightcam\\si551\\88.png", "t"], "88": ["data\\volunteers\\16M\\Clips\\straightcam\\si551\\89.png", "t"], "89": ["data\\volunteers\\16M\\Clips\\straightcam\\si551\\90.png", "t"]}}}